metslesliens/grammaire-liens.txt
metslesliens/__init__.py
metslesliens/candidats.py
metslesliens-1.3.0.dist-info/WHEEL
metslesliens-1.3.0.dist-info/METADATA
metslesliens-1.3.0.dist-info/top_level.txt
metslesliens-1.3.0.dist-info/zip-safe
metslesliens-1.3.0.dist-info/metadata.json
metslesliens-1.3.0.dist-info/RECORD
metslesliens-1.3.0.dist-info/DESCRIPTION.rst
