Metadata-Version: 2.0
Name: metslesliens
Version: 1.3.0
Summary: Mets des liens entre articles d’un texte de loi français.
Home-page: https://framagit.org/parlement-ouvert/metslesliens
Author: Seb35
Author-email: seb35pypi0@seb35.fr
License: WTFPL
Keywords: law,legal,legalese,france
Platform: Any
Classifier: Development Status :: 5 - Production/Stable
Classifier: Intended Audience :: Developers
Classifier: License :: Public Domain
Classifier: Natural Language :: French
Classifier: Operating System :: OS Independent
Classifier: Programming Language :: Python :: 3 :: Only
Classifier: Programming Language :: Python :: 3
Classifier: Programming Language :: Python :: 3.2
Classifier: Programming Language :: Python :: 3.3
Classifier: Programming Language :: Python :: 3.4
Classifier: Topic :: Text Processing :: Linguistic
Requires: parsimonious
Requires-Dist: parsimonious
